{"assests/covers/batmanBeyond.png":["assests/covers/batmanBeyond.png"],"assests/covers/ben10.png":["assests/covers/ben10.png"],"assests/covers/ben10AlienForce.png":["assests/covers/ben10AlienForce.png"],"assests/covers/ben10UltimateAlien.png":["assests/covers/ben10UltimateAlien.png"],"assests/covers/courage.png":["assests/covers/courage.png"],"assests/covers/dexter.png":["assests/covers/dexter.png"],"assests/covers/dragonBallGt.png":["assests/covers/dragonBallGt.png"],"assests/covers/fairytail2014.png":["assests/covers/fairytail2014.png"],"assests/covers/img.png":["assests/covers/img.png"],"assests/covers/jb.png":["assests/covers/jb.png"],"assests/covers/pokemon origin.png":["assests/covers/pokemon origin.png"],"assests/covers/pokemon xy.png":["assests/covers/pokemon xy.png"],"assests/covers/pokemon xyz.png":["assests/covers/pokemon xyz.png"],"assests/covers/pokemon.png":["assests/covers/pokemon.png"],"assests/covers/samuraiJack.jpg":["assests/covers/samuraiJack.jpg"],"assests/covers/scoobydoo.png":["assests/covers/scoobydoo.png"],"assests/covers/spiderman.png":["assests/covers/spiderman.png"],"assests/covers/spongebob.png":["assests/covers/spongebob.png"],"packages/cupertino_icons/assets/CupertinoIcons.ttf":["packages/cupertino_icons/assets/CupertinoIcons.ttf"],"packages/wakelock_plus/assets/no_sleep.js":["packages/wakelock_plus/assets/no_sleep.js"]}